pyutile/__init__.py
pyutile/tools.py
pyutile/config/__init__.py
pyutile/config/async_providers.py
pyutile/config/async_revalidator.py
pyutile/config/cli.py
pyutile/config/environment.py
pyutile/config/heirarchal_settings.py
pyutile/config/loader.py
pyutile/config/providers.py
pyutile/config/secure_settings.py
pyutile/config/settings.py
pyutile/config/validator.py
pyutile/config/watcher.py
pyutile/performance/__init__.py
pyutile/performance/quick.py
pyutile/reporting/__init__.py
pyutile/reporting/alerting.py
pyutile/reporting/errors.py
pyutile/reporting/logged.py
pyutile/reporting/metrics.py
pyutile/reporting/reports.py
pyutile/tests/__init__.py
pyutile/tests/configs.py
pyutile/work/__init__.py
pyutile-0.1.2.dist-info/LICENSE
pyutile-0.1.2.dist-info/METADATA
pyutile-0.1.2.dist-info/WHEEL
pyutile-0.1.2.dist-info/top_level.txt
pyutile-0.1.2.dist-info/RECORD
