Metadata-Version: 2.2
Name: pyutile
Version: 0.1.2
Summary: A PyForge Ecosytem project
Home-page: https://github.com/DirtyWork-Solutions/pyutil
Author: DirtyWork Solutions Limited
Author-email: DirtyWork Solutions Limited <pyutile@open.dirtywork.solutions>
License: Creative Commons Legal Code
Project-URL: Homepage, https://open.dirtywork.solutions/pytuile/
Project-URL: Documentation, https://github.com/DirtyWork-Solutions/pytuile/docs
Project-URL: Source, https://github.com/DirtyWork-Solutions/pytuile
Project-URL: Issues, https://github.com/DirtyWork-Solutions/pytuile/tree/main/.github/ISSUE_TEMPLATE
License-File: LICENSE
Dynamic: author
Dynamic: home-page
